py_json_to_proto/__init__.py
py_json_to_proto/cli.py
py_json_to_proto/convert.py
py_json_to_proto/example.py
py_json_to_proto-0.1.3.dist-info/entry_points.txt
py_json_to_proto-0.1.3.dist-info/WHEEL
py_json_to_proto-0.1.3.dist-info/METADATA
py_json_to_proto-0.1.3.dist-info/RECORD
