Metadata-Version: 2.1
Name: py-json-to-proto
Version: 0.1.3
Summary: file:README.md
Home-page: https://github.com/B2Gdevs/PyJsonToProto
License: MIT
Author: benjamin garrard
Author-email: benjamingarrard5279@gmail.com
Requires-Python: >=3.6.3,<4.0.0
Classifier: License :: OSI Approved :: MIT License
Classifier: Programming Language :: Python :: 3
Classifier: Programming Language :: Python :: 3.10
Classifier: Programming Language :: Python :: 3.7
Classifier: Programming Language :: Python :: 3.8
Classifier: Programming Language :: Python :: 3.9
Project-URL: Repository, https://github.com/B2Gdevs/PyJsonToProto
